gengir/__init__.py
gengir/__main__.py
gengir/analyzer.py
gengir/cli.py
gengir/generate.py
gengir/main.py
gengir/util.py
gengir-1.0.2.dist-info/entry_points.txt
gengir-1.0.2.dist-info/LICENSE
gengir-1.0.2.dist-info/WHEEL
gengir-1.0.2.dist-info/METADATA
gengir-1.0.2.dist-info/RECORD
