Metadata-Version: 2.1
Name: gengir
Version: 1.0.2
Summary: Generate PEP 561 stubs for the GObject introspection library. Forked from fakegir
Home-page: https://github.com/santiagocezar/gengir
License: GPL-3.0-or-later
Keywords: typing,type hints,gtk
Author: Santiago Cézar
Author-email: santiagocezar2013@gmail.com
Requires-Python: >=3.7,<4.0
Classifier: License :: OSI Approved :: GNU General Public License v3 or later (GPLv3+)
Classifier: Programming Language :: Python :: 3
Classifier: Programming Language :: Python :: 3.10
Classifier: Programming Language :: Python :: 3.7
Classifier: Programming Language :: Python :: 3.8
Classifier: Programming Language :: Python :: 3.9
Requires-Dist: astor (>=0.8.1,<0.9.0)
Requires-Dist: lxml (>=4.6.4,<5.0.0)
Requires-Dist: typer (>=0.4.0,<0.5.0)
Project-URL: Repository, https://github.com/santiagocezar/gengir
